tensorspacejs/__init__.py
tensorspacejs/install.py
tensorspacejs/tsp_converters.py
tensorspacejs/version.py
tensorspacejs/version.pyc
tensorspacejs/__pycache__/__init__.cpython-36.pyc
tensorspacejs/__pycache__/__init__.cpython-37.pyc
tensorspacejs/__pycache__/file_utility.cpython-36.pyc
tensorspacejs/__pycache__/install.cpython-36.pyc
tensorspacejs/__pycache__/keras_conversion.cpython-36.pyc
tensorspacejs/__pycache__/tfjs_conversion.cpython-36.pyc
tensorspacejs/__pycache__/version.cpython-36.pyc
tensorspacejs/__pycache__/version.cpython-37.pyc
tensorspacejs/krs/__init__.py
tensorspacejs/krs/__init__.pyc
tensorspacejs/krs/keras_conversion.py
tensorspacejs/krs/keras_conversion.pyc
tensorspacejs/krs/keras_model.py
tensorspacejs/krs/__pycache__/__init__.cpython-36.pyc
tensorspacejs/krs/__pycache__/keras_conversion.cpython-36.pyc
tensorspacejs/krs/__pycache__/keras_model.cpython-36.pyc
tensorspacejs/tf/__init__.py
tensorspacejs/tf/__init__.pyc
tensorspacejs/tf/frozen_model.py
tensorspacejs/tf/frozen_model.pyc
tensorspacejs/tf/keras_model.py
tensorspacejs/tf/keras_model.pyc
tensorspacejs/tf/saved_model.py
tensorspacejs/tf/saved_model.pyc
tensorspacejs/tf/tensorflow_conversion.py
tensorspacejs/tf/tensorflow_conversion.pyc
tensorspacejs/tf/__pycache__/__init__.cpython-36.pyc
tensorspacejs/tf/__pycache__/frozen_model.cpython-36.pyc
tensorspacejs/tf/__pycache__/keras_model.cpython-36.pyc
tensorspacejs/tf/__pycache__/saved_model.cpython-36.pyc
tensorspacejs/tf/__pycache__/tensorflow_conversion.cpython-36.pyc
tensorspacejs/tf/pb2json/README.md
tensorspacejs/tf/pb2json/__init__.py
tensorspacejs/tf/pb2json/__init__.pyc
tensorspacejs/tf/pb2json/package-lock.json
tensorspacejs/tf/pb2json/package.json
tensorspacejs/tf/pb2json/pb2json_conversion.py
tensorspacejs/tf/pb2json/pb2json_conversion.pyc
tensorspacejs/tf/pb2json/__pycache__/__init__.cpython-36.pyc
tensorspacejs/tf/pb2json/__pycache__/pb2json_conversion.cpython-36.pyc
tensorspacejs-0.2.0.dist-info/METADATA
tensorspacejs-0.2.0.dist-info/RECORD
tensorspacejs-0.2.0.dist-info/WHEEL
tensorspacejs-0.2.0.dist-info/entry_points.txt
tensorspacejs-0.2.0.dist-info/top_level.txt
